<annotation>
    <folder>cardTrainResized</folder>
    <filename>Kc.jpg</filename>
    <size>
        <width>490</width>
        <height>653</height>
        <depth>3</depth>
    </size>
    <segmented>0</segmented>
    <object>
        <name>12</name>
        <pose>Unspecified</pose>
        <truncated>0</truncated>
        <occluded>0</occluded>
        <difficult>0</difficult>
        <bndbox>
            <xmin>64</xmin>
            <ymin>500</ymin>
            <xmax>111</xmax>
            <ymax>618</ymax>
        </bndbox>
    </object>
    <object>
        <name>12</name>
        <pose>Unspecified</pose>
        <truncated>0</truncated>
        <occluded>0</occluded>
        <difficult>0</difficult>
        <bndbox>
            <xmin>378</xmin>
            <ymin>503</ymin>
            <xmax>424</xmax>
            <ymax>613</ymax>
        </bndbox>
    </object>
    <object>
        <name>12</name>
        <pose>Unspecified</pose>
        <truncated>0</truncated>
        <occluded>0</occluded>
        <difficult>0</difficult>
        <bndbox>
            <xmin>384</xmin>
            <ymin>54</ymin>
            <xmax>432</xmax>
            <ymax>163</ymax>
        </bndbox>
    </object>
    <object>
        <name>12</name>
        <pose>Unspecified</pose>
        <truncated>0</truncated>
        <occluded>0</occluded>
        <difficult>0</difficult>
        <bndbox>
            <xmin>77</xmin>
            <ymin>53</ymin>
            <xmax>118</xmax>
            <ymax>158</ymax>
        </bndbox>
    </object>
</annotation>